src/__init__.py
src/mapboxutil.py
mapboxutil-1.1.1.dist-info/LICENCE
mapboxutil-1.1.1.dist-info/METADATA
mapboxutil-1.1.1.dist-info/WHEEL
mapboxutil-1.1.1.dist-info/top_level.txt
mapboxutil-1.1.1.dist-info/RECORD
