Metadata-Version: 2.1
Name: mapboxutil
Version: 1.1.1
Summary: Module with utility functions to generate static choropleth maps with Mapbox
Home-page: https://mapboxutil.technetium.be
Author: Toni Cornelissen
Author-email: mapboxutil@technetium.be
License: UNKNOWN
Platform: UNKNOWN
Classifier: Programming Language :: Python :: 3
Classifier: License :: OSI Approved :: GNU General Public License v3 (GPLv3)
Classifier: Operating System :: OS Independent
Classifier: Topic :: Multimedia :: Graphics :: Presentation
Classifier: Topic :: Scientific/Engineering :: GIS
Requires-Python: >=3.5
